core/__init__.py
core/data.py
core/download.py
core/files.py
core/gui.py
core/telegram.py
core/web.py
SuperEasyPython-0.1.0.dist-info/METADATA
SuperEasyPython-0.1.0.dist-info/WHEEL
SuperEasyPython-0.1.0.dist-info/top_level.txt
SuperEasyPython-0.1.0.dist-info/RECORD
